hushh/__init__.py
hushh/_version.py
hushh/catalog.py
hushh/errors.py
hushh/hcf/Brand.py
hushh/hcf/Catalog.py
hushh/hcf/Category.py
hushh/hcf/FlatEmbeddingBatch.py
hushh/hcf/Product.py
hushh/hcf/ProductVibes.py
hushh/hcf/Vibe.py
hushh/hcf/VibeMode.py
hushh/hcf/__init__.py
hushh_vibe_catalog-0.5.0.dist-info/LICENSE
hushh_vibe_catalog-0.5.0.dist-info/METADATA
hushh_vibe_catalog-0.5.0.dist-info/WHEEL
hushh_vibe_catalog-0.5.0.dist-info/top_level.txt
hushh_vibe_catalog-0.5.0.dist-info/RECORD
