Metadata-Version: 2.1
Name: hushh-vibe-catalog
Version: 0.5.0
Author-email: Justin Donaldson <justin@hushh.ai>
License-File: LICENSE
Requires-Dist: pandas
Requires-Dist: flatbuffers
Requires-Dist: transformers
Requires-Dist: torch
Requires-Dist: Pillow
Provides-Extra: ci
Requires-Dist: pytest-cov ; extra == 'ci'
Requires-Dist: requests-mock ; extra == 'ci'
Requires-Dist: hushh-vibe-catalog[docs] ; extra == 'ci'
Provides-Extra: dev
Requires-Dist: sentence-transformers ; extra == 'dev'
Requires-Dist: kaggle ; extra == 'dev'
Requires-Dist: jupyter ; extra == 'dev'
Requires-Dist: matplotlib ; extra == 'dev'
Requires-Dist: torch ; extra == 'dev'
Requires-Dist: numpy ; extra == 'dev'
Requires-Dist: black ; extra == 'dev'
Requires-Dist: pip-tools ; extra == 'dev'
Requires-Dist: flake8 ; extra == 'dev'
Requires-Dist: bumpversion ; extra == 'dev'
Requires-Dist: hushh-vibe-catalog[ci] ; extra == 'dev'
Provides-Extra: docs
Requires-Dist: quartodoc ; extra == 'docs'
Requires-Dist: git-changelog ; extra == 'docs'
Requires-Dist: doq ; extra == 'docs'
